{
    "ret": [{
        "target": "../catalogues/counplay?tab=auto&title=Auto&typev=3",
        "text": "Auto"
      },{
        "target": "../catalogues/counplay?tab=animation&title=Animation&typev=3",
        "text": "Animation"
      },{
        "target": "../catalogues/counplay?tab=business&title=Business&typev=3",
        "text": "Business"
      },{
        "target": "../catalogues/counplay?tab=classic&title=Classic&typev=3",
        "text": "Classic"
      },{
        "target": "../catalogues/counplay?tab=comedy&title=Comedy&typev=3",
        "text": "Comedy"
      },{
        "target": "../catalogues/counplay?tab=cooking&title=Cooking&typev=3",
        "text": "Cooking"
      },{
        "target": "../catalogues/counplay?tab=culture&title=Culture&typev=3",
        "text": "Culture"
      },{
        "target": "../catalogues/counplay?tab=documentary&title=Documentary&typev=3",
        "text": "Documentary"
      },{
        "target": "../catalogues/counplay?tab=education&title=Education&typev=3",
        "text": "Education"
      },{
        "target": "../catalogues/counplay?tab=entertainment&title=Entertainment&typev=3",
        "text": "Entertainment"
      },{
        "target": "../catalogues/counplay?tab=family&title=Family&typev=3",
        "text": "Family"
      },{
        "target": "../catalogues/counplay?tab=general&title=General&typev=3",
        "text": "General"
      },{
        "target": "../catalogues/counplay?tab=kids&title=Kids&typev=3",
        "text": "Kids"
      },{
        "target": "../catalogues/counplay?tab=legislative&title=Legislative&typev=3",
        "text": "Legislative"
      },{
        "target": "../catalogues/counplay?tab=lifestyle&title=Lifestyle&typev=3",
        "text": "Lifestyle"
      },{
        "target": "../catalogues/counplay?tab=local&title=Local&typev=3",
        "text": "Local"
      },{
        "target": "../catalogues/counplay?tab=movies&title=Movies&typev=3",
        "text": "Movies"
      },{
        "target": "../catalogues/counplay?tab=music&title=Music&typev=3",
        "text": "Music"
      },{
        "target": "../catalogues/counplay?tab=news&title=News&typev=3",
        "text": "News"
      },{
        "target": "../catalogues/counplay?tab=outdoor&title=Outdoor&typev=3",
        "text": "Outdoor"
      },{
        "target": "../catalogues/counplay?tab=relax&title=Relax&typev=3",
        "text": "Relax"
      },{
        "target": "../catalogues/counplay?tab=religious&title=Religious&typev=3",
        "text": "Religious"
      },{
        "target": "../catalogues/counplay?tab=science&title=Science&typev=3",
        "text": "Science"
      },{
        "target": "../catalogues/counplay?tab=series&title=Series&typev=3",
        "text": "Series"
      },{
        "target": "../catalogues/counplay?tab=shop&title=Shop&typev=3",
        "text": "Shop"
      },{
        "target": "../catalogues/counplay?tab=sport&title=Sport&typev=3",
        "text": "Sport"
      },{
        "target": "../catalogues/counplay?tab=travel&title=Travel&typev=3",
        "text": "Travel"
      },{
        "target": "../catalogues/counplay?tab=weather&title=Weather&typev=3",
        "text": "Weather"
      },{
        "target": "../catalogues/counplay?tab=xxx&title=XXX&typev=3",
        "text": "XXX"
      },{
        "target": "../catalogues/counplay?tab=undefined&title=Other&typev=3",
        "text": "Other"
      }
    ]
  }